rarecrowds/__init__.py
rarecrowds/base_pb2.py
rarecrowds/conf_utils.py
rarecrowds/phenopackets_pb2.py
rarecrowds/rarecrowds.py
rarecrowds/resources/config.ini
rarecrowds/utils/__init__.py
rarecrowds/utils/azure_utils.py
rarecrowds/utils/disease_annotations.py
rarecrowds/utils/hpo.py
rarecrowds/utils/hpoa.py
rarecrowds/utils/mondo.py
rarecrowds/utils/ontograph.py
rarecrowds/utils/orpha.py
rarecrowds/utils/patient_sim.py
rarecrowds/utils/phenotypic_comparison.py
rarecrowds/utils/resources/hp 2.pkl
rarecrowds/utils/resources/hp.obo 2.pkl
rarecrowds/utils/resources/hp.obo.pkl
rarecrowds/utils/resources/hp.pkl
rarecrowds/utils/resources/mondo.obo 2.pkl
rarecrowds/utils/resources/mondo.obo.pkl
rarecrowds/utils/resources/orphadata_all_prods 2.pkl
rarecrowds/utils/resources/orphadata_all_prods.pkl
rarecrowds/utils/resources/orphadata_prod4_phenotypes 2.xml
rarecrowds/utils/resources/orphadata_prod4_phenotypes.xml
rarecrowds/utils/resources/orphadata_prod9_epidemiological_ages 2.xml
rarecrowds/utils/resources/orphadata_prod9_epidemiological_ages.xml
rarecrowds/utils/resources/orphadata_prod9_epidemiological_prevalence.xml
rarecrowds/utils/resources/phenotype 2.hpoa
rarecrowds/utils/resources/phenotype.hpoa
rarecrowds/utils/resources/phenotype.hpoa 2.pkl
rarecrowds/utils/resources/phenotype.hpoa.pkl
rarecrowds-0.0.5.dist-info/LICENSE
rarecrowds-0.0.5.dist-info/METADATA
rarecrowds-0.0.5.dist-info/WHEEL
rarecrowds-0.0.5.dist-info/top_level.txt
rarecrowds-0.0.5.dist-info/RECORD
